applepie/__init__.py
applepie/currencies.py
applepie/exceptions.py
applepie/pie.py
applepie-1.0.0.dist-info/METADATA
applepie-1.0.0.dist-info/RECORD
applepie-1.0.0.dist-info/WHEEL
applepie-1.0.0.dist-info/top_level.txt
