Metadata-Version: 2.1
Name: applepie
Version: 1.0.0
Summary: Apple Pay library
Home-page: https://github.com/boomletsgo/applepie
Author: Jordan Ambra
Author-email: jordan@boom.app
License: The Unlicense
Keywords: Apple Pay
Platform: UNKNOWN
Classifier: Development Status :: 5 - Production/Stable
Classifier: Intended Audience :: Developers
Classifier: Operating System :: OS Independent
Classifier: Programming Language :: Python
Classifier: Programming Language :: Python :: 2
Classifier: Programming Language :: Python :: 2.6
Classifier: Programming Language :: Python :: 2.7
Classifier: Programming Language :: Python :: 3
Classifier: Programming Language :: Python :: 3.4
Classifier: Programming Language :: Python :: 3.5
Classifier: Programming Language :: Python :: 3.6
Classifier: Topic :: Software Development :: Libraries
Requires-Dist: six (>=1.0.0)
